qtradex/__init__.py
qtradex/common/__init__.py
qtradex/common/bitshares_nodes.py
qtradex/common/json_ipc.py
qtradex/common/utilities.py
qtradex/core/__init__.py
qtradex/core/auto_backtest.py
qtradex/core/backtest.py
qtradex/core/base_bot.py
qtradex/core/dispatch.py
qtradex/core/filltest.py
qtradex/core/live.py
qtradex/core/papertrade.py
qtradex/core/quant.py
qtradex/core/tune_manager.py
qtradex/core/ui_utilities.py
qtradex/indicators/__init__.py
qtradex/indicators/cache_decorator.py
qtradex/indicators/candle_class.py
qtradex/indicators/candle_class_tests.py
qtradex/indicators/codegen.py
qtradex/indicators/fitness.py
qtradex/indicators/qi.py
qtradex/indicators/tulipy_wrapped.py
qtradex/indicators/utilities.pyx
qtradex/optimizers/__init__.py
qtradex/optimizers/aion.py
qtradex/optimizers/ipse.py
qtradex/optimizers/lsga.py
qtradex/optimizers/mouse_wheel_optimizer.py
qtradex/optimizers/qpso.py
qtradex/optimizers/utilities.py
qtradex/plot/__init__.py
qtradex/plot/utilities.py
qtradex/private/__init__.py
qtradex/private/bitshares_exchange.py
qtradex/private/execution.py
qtradex/private/signals.py
qtradex/private/wallet.py
qtradex/public/__init__.py
qtradex/public/data.py
qtradex/public/file_loader.py
qtradex/public/kibana.py
qtradex/public/kibana_queries.py
qtradex/public/klines_alphavantage.py
qtradex/public/klines_bitshares.py
qtradex/public/klines_ccxt.py
qtradex/public/klines_cryptocompare.py
qtradex/public/klines_fdr.py
qtradex/public/klines_nomics.py
qtradex/public/klines_synthetic.py
qtradex/public/klines_yahoo.py
qtradex/public/rpc.py
qtradex/public/stock_exchange_lookup.py
qtradex/public/utilities.py
qtradex-1.3.0.dist-info/licenses/LICENSE
qtradex-1.3.0.dist-info/METADATA
qtradex-1.3.0.dist-info/WHEEL
qtradex-1.3.0.dist-info/entry_points.txt
qtradex-1.3.0.dist-info/top_level.txt
qtradex-1.3.0.dist-info/RECORD
