Metadata-Version: 2.4
Name: QTradeX
Version: 1.3.0
Summary: AI-powered SDK featuring algorithmic trading, backtesting, deployment on 100+ exchanges, and multiple optimization engines.
Author: squidKid-deluxe
License: MIT
Project-URL: Homepage, https://github.com/squidKid-deluxe/QTradeX-Algo-Trading-SDK
Project-URL: Issues, https://github.com/squidKid-deluxe/QTradeX-Algo-Trading-SDK/issues
Classifier: Programming Language :: Python :: 3
Classifier: Operating System :: POSIX :: Linux
Requires-Python: >=3.9
License-File: LICENSE
Requires-Dist: ccxt
Requires-Dist: jsonpickle
Requires-Dist: cachetools
Requires-Dist: yfinance
Requires-Dist: tulipy
Requires-Dist: finance-datareader
Requires-Dist: bitshares-signing
Requires-Dist: numpy<2
Requires-Dist: matplotlib
Requires-Dist: scipy
Requires-Dist: ttkbootstrap
Dynamic: license-file
